LAB2/Q4/slave.v
module slave_fsm(
    input  wire       clk,
    input  wire       rst,
    input  wire       req,
    input  wire [7:0] data_in,
    output reg        ack,
    output reg [7:0]  last_byte
);

    reg [1:0] state, next_state;
    reg [1:0] ack_cnt;

    localparam IDLE    = 2'd0,
               ACK_HI  = 2'd1,
               ACK_HOLD = 2'd2,
               ACK_LO  = 2'd3;

    always @(posedge clk) begin
        if (rst) begin
            state <= IDLE;
            ack   <= 0;
            last_byte <= 8'h00;
            ack_cnt <= 0;
        end else begin
            state <= next_state;
            if (state == ACK_HI) begin
                ack <= 1;
                last_byte <= data_in;
                ack_cnt <= 2;
            end else if (state == ACK_HOLD && ack_cnt > 0) begin
                ack_cnt <= ack_cnt - 1;
                ack <= 1;
            end else if (state == ACK_LO) begin
                ack <= 0;
            end
        end
    end

    always @(*) begin
        next_state = state;
        case (state)
            IDLE: if (req) next_state = ACK_HI;
            ACK_HI: next_state = ACK_HOLD;
            ACK_HOLD: if (ack_cnt == 0) next_state = ACK_LO;
            ACK_LO: if (!req) next_state = IDLE;
        endcase
    end

endmodule

LAB2/Q4/master.v
module master_fsm(
    input  wire       clk,
    input  wire       rst,
    input  wire       ack,
    output reg        req,
    output reg  [7:0] data,
    output reg        done 
);

    reg [2:0] state, next_state;
    reg [1:0] byte_cnt;

    localparam IDLE   = 3'd0,
               SEND   = 3'd1,
               WAIT_ACK = 3'd2,
               DROP_REQ = 3'd3,
               WAIT_ACK_LOW = 3'd4,
               FINISH = 3'd5;

    always @(posedge clk) begin
        if (rst) begin
            state <= IDLE;
            req   <= 0;
            data  <= 8'h00;
            byte_cnt <= 0;
            done  <= 0;
        end else begin
            state <= next_state;
            if (state == FINISH)
                done <= 1;
            else
                done <= 0;
        end
    end

    // Next state and outputs
    always @(*) begin
        next_state = state;
        case (state)
            IDLE: begin
                req = 0;
                next_state = SEND;
            end

            SEND: begin
                req = 1;
                next_state = WAIT_ACK;
            end

            WAIT_ACK: begin
                req = 1;
                if (ack)
                    next_state = DROP_REQ;
            end

            DROP_REQ: begin
                req = 0;
                next_state = WAIT_ACK_LOW;
            end

            WAIT_ACK_LOW: begin
                req = 0;
                if (!ack) begin
                    if (byte_cnt == 2'd3)
                        next_state = FINISH;
                    else
                        next_state = SEND;
                end
            end

            FINISH: begin
                req = 0;
                next_state = IDLE;
            end
        endcase
    end

    // Data & byte counter updates
    always @(posedge clk) begin
        if (rst) begin
            byte_cnt <= 0;
            data <= 8'h00;
        end else begin
            if (state == SEND) begin
                data <= {6'b0, byte_cnt};
            end
            if (state == WAIT_ACK_LOW && !ack && state != FINISH) begin
                byte_cnt <= byte_cnt + 1;
            end
            if (state == FINISH)
                byte_cnt <= 0;
        end
    end

endmodule

LAB2/Q4/top.v
`include "master.v"
`include "slave.v"

module link_top(
    input  wire clk,
    input  wire rst,
    output wire done
);

    wire req, ack;
    wire [7:0] data, last_byte;

    master_fsm u_master(
        .clk(clk),
        .rst(rst),
        .ack(ack),
        .req(req),
        .data(data),
        .done(done)
    );

    slave_fsm u_slave(
        .clk(clk),
        .rst(rst),
        .req(req),
        .data_in(data),
        .ack(ack),
        .last_byte(last_byte)
    );

endmodule

LAB2/Q4/tb_top.v
`timescale 1ns/1ns
`include "top.v"

module tb_link_top;
    reg clk, rst;
    wire done;

    link_top dut(.clk(clk), .rst(rst), .done(done));

    initial begin
        clk = 0;
        forever #5 clk = ~clk;
    end

    initial begin
        rst = 1;
        #12 rst = 0;
        wait(done);
        #10 $finish;
    end

    initial begin
        $dumpfile("dump.vcd");
        $dumpvars(0, tb_link_top);
    end
endmodule

LAB2/Q4/waves/dump.vcd
$date
	Sun Aug 17 23:57:48 2025
$end
$version
	Icarus Verilog
$end
$timescale
	1ns
$end
$scope module tb_link_top $end
$var wire 1 ! done $end
$var reg 1 " clk $end
$var reg 1 # rst $end
$scope module dut $end
$var wire 1 " clk $end
$var wire 1 # rst $end
$var wire 1 $ req $end
$var wire 8 % last_byte [7:0] $end
$var wire 1 ! done $end
$var wire 8 & data [7:0] $end
$var wire 1 ' ack $end
$scope module u_master $end
$var wire 1 " clk $end
$var wire 1 # rst $end
$var wire 1 ' ack $end
$var parameter 3 ( DROP_REQ $end
$var parameter 3 ) FINISH $end
$var parameter 3 * IDLE $end
$var parameter 3 + SEND $end
$var parameter 3 , WAIT_ACK $end
$var parameter 3 - WAIT_ACK_LOW $end
$var reg 2 . byte_cnt [1:0] $end
$var reg 8 / data [7:0] $end
$var reg 1 ! done $end
$var reg 3 0 next_state [2:0] $end
$var reg 1 $ req $end
$var reg 3 1 state [2:0] $end
$upscope $end
$scope module u_slave $end
$var wire 1 " clk $end
$var wire 8 2 data_in [7:0] $end
$var wire 1 $ req $end
$var wire 1 # rst $end
$var parameter 2 3 ACK_HI $end
$var parameter 2 4 ACK_HOLD $end
$var parameter 2 5 ACK_LO $end
$var parameter 2 6 IDLE $end
$var reg 1 ' ack $end
$var reg 2 7 ack_cnt [1:0] $end
$var reg 8 8 last_byte [7:0] $end
$var reg 2 9 next_state [1:0] $end
$var reg 2 : state [1:0] $end
$upscope $end
$upscope $end
$upscope $end
$enddefinitions $end
$comment Show the parameter values. $end
$dumpall
b0 6
b11 5
b10 4
b1 3
b100 -
b10 ,
b1 +
b0 *
b101 )
b11 (
$end
#0
$dumpvars
bx :
bx 9
bx 8
bx 7
bx 2
bx 1
bx 0
bx /
bx .
x'
bx &
bx %
x$
1#
0"
x!
$end
#5
b1 0
b0 9
0!
0$
b0 1
b0 &
b0 /
b0 2
b0 .
b0 7
b0 %
b0 8
0'
b0 :
1"
#10
0"
#12
0#
#15
b1 9
b10 0
1$
b1 1
1"
#20
0"
#25
b10 9
b10 1
b1 :
1"
#30
0"
#35
b11 0
b10 7
1'
b10 :
1"
#40
0"
#45
b100 0
0$
b11 1
b1 7
1"
#50
0"
#55
b11 9
b0 7
b100 1
1"
#60
0"
#65
b0 9
b11 :
1"
#70
0"
#75
b1 0
0'
b0 :
1"
#80
0"
#85
b1 9
b10 0
1$
b1 1
b1 .
1"
#90
0"
#95
b10 9
b1 :
b1 &
b1 /
b1 2
b10 1
1"
#100
0"
#105
b11 0
b10 7
b1 %
b1 8
1'
b10 :
1"
#110
0"
#115
b100 0
0$
b1 7
b11 1
1"
#120
0"
#125
b11 9
b100 1
b0 7
1"
#130
0"
#135
b0 9
b11 :
1"
#140
0"
#145
b1 0
0'
b0 :
1"
#150
0"
#155
b1 9
b10 0
1$
b10 .
b1 1
1"
#160
0"
#165
b10 9
b10 1
b10 &
b10 /
b10 2
b1 :
1"
#170
0"
#175
b11 0
b10 7
b10 %
b10 8
1'
b10 :
1"
#180
0"
#185
b100 0
0$
b11 1
b1 7
1"
#190
0"
#195
b11 9
b0 7
b100 1
1"
#200
0"
#205
b0 9
b11 :
1"
#210
0"
#215
b1 0
0'
b0 :
1"
#220
0"
#225
b1 9
b10 0
1$
b1 1
b11 .
1"
#230
0"
#235
b10 9
b1 :
b11 &
b11 /
b11 2
b10 1
1"
#240
0"
#245
b11 0
b10 7
b11 %
b11 8
1'
b10 :
1"
#250
0"
#255
b100 0
0$
b1 7
b11 1
1"
#260
0"
#265
b11 9
b100 1
b0 7
1"
#270
0"
#275
b0 9
b11 :
1"
#280
0"
#285
b101 0
0'
b0 :
1"
#290
0"
#295
b0 0
b0 .
b101 1
1"
#300
0"
#305
b1 0
1!
b0 1
1"
#310
0"
#315
b1 9
b10 0
1$
0!
b1 1
1"
