LAB2/Q1/q1.v
module q1(
    input wire clk,
    input wire rst,
    input wire din,
    output reg y
);

parameter S0=2'b00, S1=2'b01, S2=2'b10, S3=2'b11;
reg [1:0] cur_state, next_state;

always @ (posedge clk) 
begin
    if(rst) cur_state <= S0;
    else cur_state <= next_state;
end

always @ (*) begin
    case(cur_state)
        S0: begin
            if(din) begin
                next_state = S1;
                y=0;
            end
            else begin
                next_state = S0;
                y=0;
            end
        end
        S1: begin
            if(din) begin
                next_state = S2;
                y=0;
            end
            else begin
                next_state = S0;
                y=0;
            end
        end
        S2: begin
            if(din) begin
                next_state = S2;
                y=0;
            end
            else begin
                next_state = S3;
                y=0;
            end
        end
        S3: begin
            if(din) begin
                next_state = S1;
                y=1;
            end
            else begin
                next_state = S0;
                y=0;
            end
        end
        default: begin
            next_state = cur_state;
            y=0;
        end
    endcase
end
endmodule

LAB2/Q1/q1_tb.v
`timescale 1ns/1ns
`include "q1.v"

module tb_q1;

    reg clk, rst, din;
    wire y;

    q1 uut (
        .clk(clk),
        .rst(rst),
        .din(din),
        .y(y)
    );

    always #5 clk = ~clk;

    initial begin
        $dumpfile("dump.vcd");
        $dumpvars(0, tb_q1);

        clk = 0;
        rst = 1;
        din = 0;

        #10;
        rst = 0;

        #10 din = 1;
        #10 din = 1;
        #10 din = 0;
        #10 din = 1;
        #10 din = 0;
        #10 din = 1;
        #10 din = 1;
        #10 din = 1;
        #10 din = 0;
        #10 din = 1;

        #20 $finish;
    end

endmodule

LAB2/Q1/waves/dump.vcd
$date
	Sun Aug 17 14:29:15 2025
$end
$version
	Icarus Verilog
$end
$timescale
	1ns
$end
$scope module tb_q1 $end
$var wire 1 ! y $end
$var reg 1 " clk $end
$var reg 1 # din $end
$var reg 1 $ rst $end
$scope module uut $end
$var wire 1 " clk $end
$var wire 1 # din $end
$var wire 1 $ rst $end
$var parameter 2 % S0 $end
$var parameter 2 & S1 $end
$var parameter 2 ' S2 $end
$var parameter 2 ( S3 $end
$var reg 2 ) cur_state [1:0] $end
$var reg 2 * next_state [1:0] $end
$var reg 1 ! y $end
$upscope $end
$upscope $end
$enddefinitions $end
$comment Show the parameter values. $end
$dumpall
b11 (
b10 '
b1 &
b0 %
$end
#0
$dumpvars
bx *
bx )
1$
0#
0"
0!
$end
#5
b0 *
b0 )
1"
#10
0"
0$
#15
1"
#20
b1 *
0"
1#
#25
b10 *
b1 )
1"
#30
0"
#35
b10 )
1"
#40
b11 *
0"
0#
#45
b0 *
b11 )
1"
#50
1!
b1 *
0"
1#
#55
0!
b10 *
b1 )
1"
#60
b0 *
0"
0#
#65
b0 )
1"
#70
b1 *
0"
1#
#75
b10 *
b1 )
1"
#80
0"
#85
b10 )
1"
#90
0"
#95
1"
#100
b11 *
0"
0#
#105
b0 *
b11 )
1"
#110
1!
b1 *
0"
1#
#115
0!
b10 *
b1 )
1"
#120
0"
#125
b10 )
1"
