LAB2/Q2/q2.v
module q2(
    input wire clk,
    input wire rst,
    output reg ns_g,ns_y,ns_r,
    output reg ew_g,ew_y,ew_r
);

parameter s_ns_g=2'b00,s_ns_y=2'b01,s_ew_g=2'b10,s_ew_y=2'b11;
reg cur_state,next_state;
reg [2:0] timer;

always @ (posedge clk) begin
    if(rst) begin
        cur_state <= s_ns_g;
        timer <= 3'd0;
    end
    else begin
        cur_state <= next_state;
        if(cur_state!=next_state) timer <= 3'd0;
        else timer <= timer+1;
    end
end

always @ (*) begin
    next_state = cur_state;
    case(cur_state)
        s_ns_g: if(timer==3'd4) next_state=s_ns_y;
        s_ns_y: if(timer==3'd1) next_state=s_ew_g;
        s_ew_g: if(timer==3'd4) next_state=s_ew_y;
        s_ew_y: if(timer==3'd1) next_state=s_ns_g;
    endcase
end

always @ (*) begin
    ns_g=0;
    ns_y=0;
    ns_r=0;
    ew_g=0;
    ew_y=0;
    ew_r=0;
    case(cur_state) 
        s_ns_g: begin
            ns_g=1;
            ew_r=1;
        end
        s_ns_y: begin
            ns_y=1;
            ew_r=1;
        end
        s_ew_g: begin
            ew_g=1;
            ns_r=1;
        end
        s_ew_y: begin
            ew_y=1;
            ns_r=1;
        end
    endcase
end
endmodule

LAB2/Q2/q2_tb.v
`timescale 1ns/1ns
`include "q2.v"

module q2_tb;

    reg clk, rst;
    wire ns_g, ns_y, ns_r, ew_g, ew_y, ew_r;

    q2 dut (
        .clk(clk),
        .rst(rst),
        .ns_g(ns_g), .ns_y(ns_y), .ns_r(ns_r),
        .ew_g(ew_g), .ew_y(ew_y), .ew_r(ew_r)
    );

    always #5 clk = ~clk;

    initial begin
        $dumpfile("dump.vcd");
        $dumpvars(0, q2_tb);

        clk = 0;
        rst = 1;

        #12;
        rst = 0;

        #300;
        $finish;
    end

    // initial begin
    //     $display("Time\tclk\trst\tNS(g,y,r)\tEW(g,y,r)");
    //     $monitor("%0t\t%b\t%b\t%b %b %b\t%b %b %b",
    //              $time, clk, rst,
    //              ns_g, ns_y, ns_r,
    //              ew_g, ew_y, ew_r);
    // end

endmodule

LAB2/Q2/waves/dump.vcd
$date
	Sun Aug 17 15:34:02 2025
$end
$version
	Icarus Verilog
$end
$timescale
	1ns
$end
$scope module q2_tb $end
$var wire 1 ! ns_y $end
$var wire 1 " ns_r $end
$var wire 1 # ns_g $end
$var wire 1 $ ew_y $end
$var wire 1 % ew_r $end
$var wire 1 & ew_g $end
$var reg 1 ' clk $end
$var reg 1 ( rst $end
$scope module dut $end
$var wire 1 ' clk $end
$var wire 1 ( rst $end
$var parameter 2 ) s_ew_g $end
$var parameter 2 * s_ew_y $end
$var parameter 2 + s_ns_g $end
$var parameter 2 , s_ns_y $end
$var reg 1 - cur_state $end
$var reg 1 & ew_g $end
$var reg 1 % ew_r $end
$var reg 1 $ ew_y $end
$var reg 1 . next_state $end
$var reg 1 # ns_g $end
$var reg 1 " ns_r $end
$var reg 1 ! ns_y $end
$var reg 3 / timer [2:0] $end
$upscope $end
$upscope $end
$enddefinitions $end
$comment Show the parameter values. $end
$dumpall
b1 ,
b0 +
b11 *
b10 )
$end
#0
$dumpvars
bx /
x.
x-
1(
0'
x&
x%
x$
x#
x"
x!
$end
#5
1%
0$
0&
0"
0!
1#
0.
b0 /
0-
1'
#10
0'
#12
0(
#15
b1 /
1'
#20
0'
#25
b10 /
1'
#30
0'
#35
b11 /
1'
#40
0'
#45
1.
b100 /
1'
#50
0'
#55
1!
1%
0#
b0 /
1-
1'
#60
0'
#65
0.
b1 /
1'
#70
0'
#75
1#
1%
0!
b0 /
0-
1'
#80
0'
#85
b1 /
1'
#90
0'
#95
b10 /
1'
#100
0'
#105
b11 /
1'
#110
0'
#115
1.
b100 /
1'
#120
0'
#125
1!
1%
0#
b0 /
1-
1'
#130
0'
#135
0.
b1 /
1'
#140
0'
#145
1#
1%
0!
b0 /
0-
1'
#150
0'
#155
b1 /
1'
#160
0'
#165
b10 /
1'
#170
0'
#175
b11 /
1'
#180
0'
#185
1.
b100 /
1'
#190
0'
#195
1!
1%
0#
b0 /
1-
1'
#200
0'
#205
0.
b1 /
1'
#210
0'
#215
1#
1%
0!
b0 /
0-
1'
#220
0'
#225
b1 /
1'
#230
0'
#235
b10 /
1'
#240
0'
#245
b11 /
1'
#250
0'
#255
1.
b100 /
1'
#260
0'
#265
1!
1%
0#
b0 /
1-
1'
#270
0'
#275
0.
b1 /
1'
#280
0'
#285
1#
1%
0!
b0 /
0-
1'
#290
0'
#295
b1 /
1'
#300
0'
#305
b10 /
1'
