LAB2/Q3/q3.v
module q3(
    input wire clk,
    input wire rst,
    input wire [1:0] coin,
    output reg dispense,
    output reg chg5
);

parameter S0=3'b000,
          S5=3'b001,
          S10=3'b010,
          S15=3'b011,
          S20=3'b100;

reg [2:0] cur_state, next_state;

always @ (posedge clk) begin
    if(rst) begin
        cur_state <= S0;
    end
    else begin
        cur_state <= next_state;
    end
end

always @ (*) begin
    dispense = 0;
    chg5 = 0;
    
    case(cur_state)
        S0: begin
            if(coin == 2'b01)      // 5-unit coin
                next_state = S5;
            else if(coin == 2'b10) // 10-unit coin
                next_state = S10;
            else                   // idle (coin == 2'b00 or invalid)
                next_state = cur_state;
        end
        
        S5: begin
            if(coin == 2'b01)      // 5 + 5 = 10
                next_state = S10;
            else if(coin == 2'b10) // 5 + 10 = 15
                next_state = S15;
            else                   // idle
                next_state = cur_state;
        end
        
        S10: begin
            if(coin == 2'b01)      // 10 + 5 = 15
                next_state = S15;
            else if(coin == 2'b10) // 10 + 10 = 20 (exact payment)
                next_state = S20;
            else                   // idle
                next_state = cur_state;
        end
        
        S15: begin
            if(coin == 2'b01) begin
                next_state = S20;
            end
            else if(coin == 2'b10) begin
                next_state = S0;
                dispense = 1;
                chg5 = 1;
            end
            else
                next_state = cur_state;
        end
        
        S20: begin
            next_state = S0;
            dispense = 1;
        end
        
        default: begin
            next_state = S0;
        end
    endcase
end

endmodule

LAB2/Q3/q3_tb.v
`timescale 1ns/1ns
`include "q3.v"

module tb_q3;

    reg clk = 0, rst = 1;
    reg [1:0] coin = 2'b00;     // 01 = 5, 10 = 10, 00 = idle
    wire dispense, chg5;

    // DUT instantiation
    q3 dut (
        .clk(clk),
        .rst(rst),
        .coin(coin),
        .dispense(dispense),
        .chg5(chg5)
    );

    // Clock: 10 ns period
    always #5 clk = ~clk;

    // VCD dump for GTKWave
    initial begin
        $dumpfile("dump.vcd");
        $dumpvars(0, tb_q3);
    end

    // Console monitor
    // initial begin
    //     $display(" time | coin dispense chg5");
    //     $monitor("%4t |  %b      %b       %b",
    //              $time, coin, dispense, chg5);
    // end

    // Stimulus
    initial begin
        // Reset for 2 cycles
        repeat(2) @(posedge clk);
        rst = 0;

        // Case 1: 5 + 5 + 10 = 20 (dispense)
        pay5(); pay5(); pay10();
        @(posedge clk);

        // Case 2: 10 + 10 = 20 (dispense)
        pay10(); pay10();
        @(posedge clk);

        // Case 3: 5 + 10 + 10 = 25 (dispense + change)
        pay5(); pay10(); pay10();
        @(posedge clk);

        // Case 4: 10 + 5 + 10 = 25 (dispense + change)
        pay10(); pay5(); pay10();
        @(posedge clk);

        // Case 5: Overpay with (10 + 10 + 5) → should reset after dispense
        pay10(); pay10(); pay5();
        @(posedge clk);

        #30 $finish;
    end

    // --- helper tasks for coins ---
    task pay5; begin
        @(negedge clk); coin = 2'b01;
        @(posedge clk); // sampled
        @(negedge clk); coin = 2'b00; // release
    end endtask

    task pay10; begin
        @(negedge clk); coin = 2'b10;
        @(posedge clk);
        @(negedge clk); coin = 2'b00;
    end endtask

endmodule

LAB2/Q3/waves/dump.vcd
$date
	Sun Aug 17 18:36:25 2025
$end
$version
	Icarus Verilog
$end
$timescale
	1ns
$end
$scope module tb_q3 $end
$var wire 1 ! dispense $end
$var wire 1 " chg5 $end
$var reg 1 # clk $end
$var reg 2 $ coin [1:0] $end
$var reg 1 % rst $end
$scope module dut $end
$var wire 1 # clk $end
$var wire 2 & coin [1:0] $end
$var wire 1 % rst $end
$var parameter 3 ' S0 $end
$var parameter 3 ( S10 $end
$var parameter 3 ) S15 $end
$var parameter 3 * S20 $end
$var parameter 3 + S5 $end
$var reg 1 " chg5 $end
$var reg 3 , cur_state [2:0] $end
$var reg 1 ! dispense $end
$var reg 3 - next_state [2:0] $end
$upscope $end
$scope task pay10 $end
$upscope $end
$scope task pay5 $end
$upscope $end
$upscope $end
$enddefinitions $end
$comment Show the parameter values. $end
$dumpall
b1 +
b100 *
b11 )
b10 (
b0 '
$end
#0
$dumpvars
b0 -
bx ,
b0 &
1%
b0 $
0#
0"
0!
$end
#5
b0 ,
1#
#10
0#
#15
0%
1#
#20
b1 -
b1 $
b1 &
0#
#25
b10 -
b1 ,
1#
#30
b1 -
b0 $
b0 &
0#
#35
1#
#40
b10 -
b1 $
b1 &
0#
#45
b11 -
b10 ,
1#
#50
b10 -
b0 $
b0 &
0#
#55
1#
#60
b100 -
b10 $
b10 &
0#
#65
1!
b0 -
b100 ,
1#
#70
1!
b0 $
b0 &
0#
#75
0!
b0 ,
1#
#80
b10 -
b10 $
b10 &
0#
#85
b100 -
b10 ,
1#
#90
b10 -
b0 $
b0 &
0#
#95
1#
#100
b100 -
b10 $
b10 &
0#
#105
1!
b0 -
b100 ,
1#
#110
1!
b0 $
b0 &
0#
#115
0!
b0 ,
1#
#120
b1 -
b1 $
b1 &
0#
#125
b10 -
b1 ,
1#
#130
b1 -
b0 $
b0 &
0#
#135
1#
#140
b11 -
b10 $
b10 &
0#
#145
1"
1!
b0 -
b11 ,
1#
#150
b11 -
0"
0!
b0 $
b0 &
0#
#155
1#
#160
1"
1!
b0 -
b10 $
b10 &
0#
#165
b10 -
0"
0!
b0 ,
1#
#170
b0 -
b0 $
b0 &
0#
#175
1#
#180
b10 -
b10 $
b10 &
0#
#185
b100 -
b10 ,
1#
#190
b10 -
b0 $
b0 &
0#
#195
1#
#200
b11 -
b1 $
b1 &
0#
#205
b100 -
b11 ,
1#
#210
b11 -
b0 $
b0 &
0#
#215
1#
#220
1"
1!
b0 -
b10 $
b10 &
0#
#225
b10 -
0"
0!
b0 ,
1#
#230
b0 -
b0 $
b0 &
0#
#235
1#
#240
b10 -
b10 $
b10 &
0#
#245
b100 -
b10 ,
1#
#250
b10 -
b0 $
b0 &
0#
#255
1#
#260
b100 -
b10 $
b10 &
0#
#265
1!
b0 -
b100 ,
1#
#270
1!
b0 $
b0 &
0#
#275
0!
b0 ,
1#
#280
b1 -
b1 $
b1 &
0#
#285
b10 -
b1 ,
1#
#290
b1 -
b0 $
b0 &
0#
